synergy/__init__.py
synergy/exception.py
synergy/service.py
synergy/auth/__init__.py
synergy/auth/plugin.py
synergy/client/__init__.py
synergy/client/command.py
synergy/client/exception.py
synergy/client/keystone_v3.py
synergy/client/shell.py
synergy/client/tabulate.py
synergy/common/__init__.py
synergy/common/command.py
synergy/common/config.py
synergy/common/context.py
synergy/common/manager.py
synergy/common/serializer.py
synergy/common/service.py
synergy/common/utils.py
synergy/common/wsgi.py
synergy/examples/__init__.py
synergy/examples/timer_manager.py
synergy/tests/__init__.py
synergy/tests/base.py
synergy/tests/functional/__init__.py
synergy/tests/functional/test_synergy.py
synergy/tests/unit/__init__.py
synergy/tests/unit/test_client_command_executecommand.py
synergy/tests/unit/test_client_command_httpcommand.py
synergy/tests/unit/test_client_command_managercommand.py
synergy/tests/unit/test_client_shell.py
synergy/tests/unit/test_manager_abstract.py
synergy/tests/unit/test_manager_implementation.py
synergy/tests/unit/test_serializer.py
synergy_service-1.5.3.data/scripts/synergy
synergy_service-1.5.3.data/scripts/synergy-service
synergy_service-1.5.3.dist-info/DESCRIPTION.rst
synergy_service-1.5.3.dist-info/METADATA
synergy_service-1.5.3.dist-info/RECORD
synergy_service-1.5.3.dist-info/WHEEL
synergy_service-1.5.3.dist-info/entry_points.txt
synergy_service-1.5.3.dist-info/metadata.json
synergy_service-1.5.3.dist-info/pbr.json
synergy_service-1.5.3.dist-info/top_level.txt
