Metadata-Version: 2.0
Name: synergy-service
Version: 1.5.3
Summary: Synergy is as an extensible general purpose management OpenStack service.
Home-page: https://launchpad.net/synergy-service
Author: Lisa Zangrando
Author-email: lisa.zangrando@pd.infn.it
License: UNKNOWN
Platform: UNKNOWN
Classifier: Environment :: OpenStack
Classifier: Intended Audience :: Information Technology
Classifier: Intended Audience :: System Administrators
Classifier: License :: OSI Approved :: Apache Software License
Classifier: Operating System :: POSIX :: Linux
Classifier: Programming Language :: Python
Classifier: Programming Language :: Python :: 2
Classifier: Programming Language :: Python :: 2.7
Requires-Dist: pbr
Requires-Dist: eventlet
Requires-Dist: oslo.config
Requires-Dist: python-dateutil
Requires-Dist: requests
